fastapi_oauth_rbac/__init__.py
fastapi_oauth_rbac/alembic/env.py
fastapi_oauth_rbac/auth/oauth.py
fastapi_oauth_rbac/auth/router.py
fastapi_oauth_rbac/core/audit.py
fastapi_oauth_rbac/core/config.py
fastapi_oauth_rbac/core/email.py
fastapi_oauth_rbac/core/hooks.py
fastapi_oauth_rbac/core/security.py
fastapi_oauth_rbac/dashboard/router.py
fastapi_oauth_rbac/dashboard/templates/access_denied.html.jinja
fastapi_oauth_rbac/dashboard/templates/audit.html.jinja
fastapi_oauth_rbac/dashboard/templates/index.html.jinja
fastapi_oauth_rbac/dashboard/templates/layouts/base.html.jinja
fastapi_oauth_rbac/dashboard/templates/login.html.jinja
fastapi_oauth_rbac/dashboard/templates/roles.html.jinja
fastapi_oauth_rbac/database/models.py
fastapi_oauth_rbac/database/session.py
fastapi_oauth_rbac/main.py
fastapi_oauth_rbac/py.typed
fastapi_oauth_rbac/rbac/dependencies.py
fastapi_oauth_rbac/rbac/logic.py
fastapi_oauth_rbac/rbac/manager.py
fastapi_oauth_rbac/testing.py
fastapi_oauth_rbac-0.1.4.dist-info/WHEEL
fastapi_oauth_rbac-0.1.4.dist-info/METADATA
fastapi_oauth_rbac-0.1.4.dist-info/RECORD
