Metadata-Version: 2.3
Name: fastapi-oauth-rbac
Version: 0.1.4
Summary: A comprehensive FastAPI library for Authentication and NIST-style Role-Based Access Control (RBAC) with SQLAlchemy support.
Author: Fernando
Author-email: Fernando <fernando@softpoint.es>
Requires-Dist: alembic>=1.18.3
Requires-Dist: argon2-cffi>=25.1.0
Requires-Dist: email-validator>=2.2.0
Requires-Dist: fastapi>=0.128.0
Requires-Dist: httpx>=0.28.1
Requires-Dist: jinja2>=3.1.6
Requires-Dist: pwdlib[argon2]>=0.3.0
Requires-Dist: pydantic-settings>=2.12.0
Requires-Dist: pytest-asyncio>=1.3.0
Requires-Dist: python-jose[cryptography]>=3.5.0
Requires-Dist: python-multipart>=0.0.22
Requires-Dist: sqlalchemy[asyncio]>=2.0.46
Requires-Dist: uvicorn>=0.34.0
Requires-Dist: asyncpg>=0.29.0 ; extra == 'postgres'
Requires-Dist: aiosqlite>=0.20.0 ; extra == 'sqlite'
Requires-Python: >=3.10
Provides-Extra: postgres
Provides-Extra: sqlite
